{
  "usuarios": [
    {
      "id": "1000638705",
      "name": "Juan Diego",
      "pending": false,
      "lastName": "Londono Chavarria",
      "email": "juandiego0329@gmail.com",
      "password": "password",
      "category": "Administrador",
      "deleted": 0
    },
    {
      "id": "1000635820",
      "name": "Jader Daniel",
      "pending": false,
      "lastName": "Atehortúa Zapata",
      "email": "daniel0606zapata@gmail.com",
      "password": "123",
      "category": "Administrador",
      "deleted": 0
    },
    {
      "id": "mario",
      "name": "Mario",
      "pending": false,
      "lastName": "Saldarriaga",
      "email": "alejocol96@gmail.com",
      "password": "mario123",
      "category": "Administrador",
      "deleted": 0
    },
    {
      "id": "1000763295",
      "name": "Jhon",
      "pending": false,
      "lastName": "Aviles",
      "email": "aviles52ruiz@gmail.com",
      "password": "jhon123",
      "category": "Administrador",
      "deleted": 0
    },
    {
      "id": "123456",
      "name": "Pablo",
      "pending": false,
      "lastName": "Gonzalez",
      "email": "pablito@gmail.com",
      "password": "123",
      "category": "Conductor",
      "deleted": 1
    },
    {
      "id": "1234",
      "name": "Pedro",
      "pending": true,
      "lastName": "Perez",
      "email": "pedroperez@gmail.com",
      "password": "pedrito",
      "category": "Conductor",
      "deleted": 0
    },
    {
      "id": "xD",
      "name": "xD",
      "pending": false,
      "lastName": "xD",
      "email": "xD@gmail.com",
      "password": "xD",
      "category": "Conductor",
      "deleted": 1
    },
    {
      "id": "3507",
      "name": "Pedro",
      "pending": true,
      "lastName": "Infante",
      "email": "pedritopepito@yopmail.com",
      "password": "123",
      "category": "Conductor",
      "deleted": 0
    }
  ],
  "rutas": [
    {
      "id": "123789",
      "salida": "Florencia",
      "llegada": "Robledo",
      "observation": "No"
    }
  ],
  "recordatorios": [
    {
      "id": 2,
      "title": "Vista al frente",
      "msg": "Estudiantes de ingenieria descansando en el camino"
    },
    {
      "id": 3,
      "title": "Cuidado",
      "msg": "Jotos cerca"
    },
    {
      "id": 4,
      "title": "Ojo",
      "msg": "Otakus en el camino"
    },
    {
      "id": 6,
      "title": "Ojo",
      "msg": "Jugadores de free fire en el bosque"
    },
    {
      "id": 7,
      "title": "Atencion",
      "msg": "Mango vendiendo obleas"
    },
    {
      "id": 8,
      "title": "Oe",
      "msg": "Vieja sin ojos en la ruta"
    },
    {
      "id": 9,
      "title": "Jajsjajaja",
      "msg": "mimamamemima"
    },
    {
      "id": 10,
      "title": "xd",
      "msg": "xd"
    },
    {
      "title": "Ay mi madre el bicho",
      "msg": "Ola",
      "id": 11
    }
  ]
}